common_utils_data/__init__.py
common_utils_data/config_table.py
common_utils_data/data_handle_func.py
common_utils_data/data_handle_sheet_func.py
common_utils_data/data_process_func.py
common_utils_data/data_statistic_func.py
common_utils_data/decorator_functions.py
common_utils_data/df_functions.py
common_utils_data/excel_functions.py
common_utils_data/func_classes.py
common_utils_data/get_sql_data.py
common_utils_data/highlight_kw.py
common_utils_data/information.py
common_utils_data/jupyter_functions.py
common_utils_data/nlp_functions.py
common_utils_data/nltk_functions.py
common_utils_data/os_functions.py
common_utils_data/regex_functions.py
common_utils_data/sequence_functions.py
common_utils_data/sql_functions.py
common_utils_data-0.0.9.dist-info/LICENSE
common_utils_data-0.0.9.dist-info/METADATA
common_utils_data-0.0.9.dist-info/WHEEL
common_utils_data-0.0.9.dist-info/top_level.txt
common_utils_data-0.0.9.dist-info/RECORD
