Metadata-Version: 2.1
Name: common-utils-data
Version: 0.0.9
Summary: Fix bugs in the wrong imports
Home-page: https://github.com/Mi524/common_utils_pkg
Author: Tracy Tang
Author-email: tracytang58@icloud.com
Project-URL: Bug Tracker, https://github.com/Mi524/common_utils_pkg/issues
Classifier: Programming Language :: Python :: 3
Classifier: License :: OSI Approved :: MIT License
Classifier: Operating System :: OS Independent
Requires-Python: >=3.6
License-File: LICENSE
Requires-Dist: pandas (>=1.2.0)
Requires-Dist: numpy
Requires-Dist: openpyxl
Requires-Dist: xlsxwriter
Requires-Dist: xlwings
Requires-Dist: html5lib
Requires-Dist: lxml
Requires-Dist: sqlalchemy (>=1.3.22)
Requires-Dist: pymysql (>=1.0.2)
Requires-Dist: mysql-client
Requires-Dist: flashtext
Requires-Dist: swifter (>=1.0.7)
Requires-Dist: cx-Oracle
